tomacco
