Metadata-Version: 1.1
Name: tomacco
Version: 0.4.4
Summary: Pomodoro Technique time
Home-page: http://github.com/axce1/tomacco
Author: axce1
Author-email: axce1.github@gmail.com
License: WTFPL
Platform: Linux
Classifier: Programming Language :: Python :: 3
Classifier: Programming Language :: Python :: 3.3
Classifier: Programming Language :: Python :: 3.4
